docseer/__init__.py
docseer/__main__.py
docseer/config.py
docseer/ui.py
docseer/agents/__init__.py
docseer/agents/basic_agent.py
docseer/agents/utils.py
docseer/chunkers/__init__.py
docseer/chunkers/docling_chunker.py
docseer/chunkers/parent_child_chunker.py
docseer/converters/__init__.py
docseer/converters/content_extractor.py
docseer/converters/converter.py
docseer/converters/metadata_extractor.py
docseer/converters/utils.py
docseer/databases/__init__.py
docseer/databases/chroma.py
docseer/databases/localfilestore.py
docseer/documents/__init__.py
docseer/documents/documents.py
docseer/documents/utils.py
docseer/retrievers/__init__.py
docseer/retrievers/async_flashrankrerank.py
docseer/retrievers/multi_steps_retriever.py
docseer/retrievers/mutli_query.py
docseer/retrievers/retriever.py
docseer-0.3.1.dist-info/licenses/LICENSE
docseer-0.3.1.dist-info/METADATA
docseer-0.3.1.dist-info/WHEEL
docseer-0.3.1.dist-info/entry_points.txt
docseer-0.3.1.dist-info/top_level.txt
docseer-0.3.1.dist-info/RECORD
