Metadata-Version: 2.4
Name: docseer
Version: 0.3.1
Summary: DocSeer: Summarize and understand your documents at a glance.
Author-email: Mohammed Fellaji <fellajimohammed@gmail.com>
License: MIT
Requires-Python: >=3.12
License-File: LICENSE
Requires-Dist: transformers>=4.52.1
Requires-Dist: rich>=14.0.0
Requires-Dist: PyMuPDF>=1.25.5
Requires-Dist: types-requests>=2.32.0.20250515
Requires-Dist: langchain>=0.3.25
Requires-Dist: langchain-ollama>=0.3.6
Requires-Dist: langchain-chroma>=0.2.5
Requires-Dist: sentence-transformers>=4.1.0
Requires-Dist: faiss-cpu>=1.11.0
Requires-Dist: hf-xet>=1.1.2
Requires-Dist: docling>=2.46.0
Requires-Dist: flashrank>=0.2.10
Requires-Dist: langchain-community>=0.3.27
Requires-Dist: pydantic-ai>=0.8.1
Requires-Dist: pydantic>=2.11.7
Requires-Dist: langchain-text-splitters>=1.0.0
Dynamic: license-file
